raspaSPIUnet/__init__.py
raspaSPIUnet-0.1.2.dist-info/LICENSE
raspaSPIUnet-0.1.2.dist-info/METADATA
raspaSPIUnet-0.1.2.dist-info/WHEEL
raspaSPIUnet-0.1.2.dist-info/top_level.txt
raspaSPIUnet-0.1.2.dist-info/RECORD
