Metadata-Version: 2.1
Name: raspaSPIUnet
Version: 0.1.2
Summary: Raspador para SPIUnet.
Home-page: https://github.com/memoriadecalculo/raspaSPIUnet
Author: Memória de Cálculo
Author-email: memoriadcalculo@gmail.com
License: MIT
Classifier: Environment :: Web Environment
Classifier: License :: OSI Approved :: MIT License
Classifier: Operating System :: OS Independent
Classifier: Programming Language :: Python
Classifier: Programming Language :: Python :: 3
Classifier: Programming Language :: Python :: 3 :: Only
Classifier: Programming Language :: Python :: 3.6
Classifier: Programming Language :: Python :: 3.7
Classifier: Programming Language :: Python :: 3.8
Classifier: Topic :: Internet :: WWW/HTTP
Classifier: Topic :: Internet :: WWW/HTTP :: Dynamic Content
License-File: LICENSE
Requires-Dist: bs4
Requires-Dist: selenium
